docs/nb_gen/__init__.py
docs/nb_gen/__main__.py
docs/nb_gen/doc_tables.py
docs/nb_gen/gen_question_notebooks.py
docs/nb_gen/schema.py
docs/nb_gen_tests/__init__.py
docs/nb_gen_tests/conftest.py
docs/nb_gen_tests/test_doc_tablen_gen.py
docs/nb_gen_tests/test_notebook.py
docs/nb_gen_tests/test_schema.py
docs/nb_gen_tests/test_specifiers_md.py
docs/source/conf.py
jupyter_notebooks/drift_helper.py
jupyter_notebooks/startup.py
pybatfish/__init__.py
pybatfish/exception.py
pybatfish/py.typed
pybatfish/util.py
pybatfish/client/__init__.py
pybatfish/client/_facts.py
pybatfish/client/asserts.py
pybatfish/client/capirca.py
pybatfish/client/consts.py
pybatfish/client/internal.py
pybatfish/client/options.py
pybatfish/client/restv2helper.py
pybatfish/client/session.py
pybatfish/client/workhelper.py
pybatfish/client/workitem.py
pybatfish/datamodel/__init__.py
pybatfish/datamodel/acl.py
pybatfish/datamodel/flow.py
pybatfish/datamodel/primitives.py
pybatfish/datamodel/referencelibrary.py
pybatfish/datamodel/route.py
pybatfish/datamodel/answer/__init__.py
pybatfish/datamodel/answer/base.py
pybatfish/datamodel/answer/table.py
pybatfish/question/__init__.py
pybatfish/question/question.py
pybatfish/question/questionutil.py
pybatfish/settings/__init__.py
pybatfish/settings/issues.py
pybatfish-2025.7.7.2423.dist-info/licenses/LICENSE
tests/client/test_assert.py
tests/client/test_capirca.py
tests/client/test_commands.py
tests/client/test_facts.py
tests/client/test_questions.py
tests/client/test_restv2helper.py
tests/client/test_session.py
tests/client/test_workhelper.py
tests/datamodel/__init__.py
tests/datamodel/test_acltrace.py
tests/datamodel/test_auto_complete_suggestion.py
tests/datamodel/test_datamodel_element.py
tests/datamodel/test_filelines.py
tests/datamodel/test_flow.py
tests/datamodel/test_flowtracehop.py
tests/datamodel/test_interface.py
tests/datamodel/test_issue.py
tests/datamodel/test_primitives.py
tests/datamodel/test_referencelibrary.py
tests/datamodel/test_route.py
tests/datamodel/test_session.py
pybatfish-2025.7.7.2423.dist-info/METADATA
pybatfish-2025.7.7.2423.dist-info/WHEEL
pybatfish-2025.7.7.2423.dist-info/entry_points.txt
pybatfish-2025.7.7.2423.dist-info/top_level.txt
pybatfish-2025.7.7.2423.dist-info/RECORD
