Metadata-Version: 2.4
Name: pybatfish
Version: 2025.7.7.2423
Summary: Python API and utilities for Batfish
Author-email: The Batfish Open Source Project <pybatfish-dev@intentionet.com>
License: Apache License 2.0
Project-URL: Homepage, https://github.com/batfish/pybatfish
Project-URL: Documentation, https://pybatfish.readthedocs.io/en/latest/
Project-URL: Repository, https://github.com/batfish/pybatfish
Keywords: network,configuration,verification
Classifier: Development Status :: 3 - Alpha
Classifier: Intended Audience :: Developers
Classifier: Topic :: Software Development :: Libraries :: Python Modules
Classifier: License :: OSI Approved :: Apache Software License
Classifier: Programming Language :: Python :: 3
Classifier: Programming Language :: Python :: 3 :: Only
Classifier: Programming Language :: Python :: 3.9
Classifier: Programming Language :: Python :: 3.10
Classifier: Programming Language :: Python :: 3.11
Classifier: Programming Language :: Python :: 3.12
Classifier: Programming Language :: Python :: 3.13
Requires-Python: >=3.9
License-File: LICENSE
Requires-Dist: attrs>=18.1.0
Requires-Dist: deepdiff
Requires-Dist: pandas
Requires-Dist: python-dateutil
Requires-Dist: PyYAML
Requires-Dist: requests
Requires-Dist: requests-toolbelt
Requires-Dist: setuptools
Requires-Dist: simplejson
Requires-Dist: urllib3>=1.26.0
Provides-Extra: capirca
Requires-Dist: capirca; extra == "capirca"
Requires-Dist: absl-py>=0.8.0; extra == "capirca"
Provides-Extra: dev
Requires-Dist: black<23.11; extra == "dev"
Requires-Dist: cerberus; extra == "dev"
Requires-Dist: check-manifest; extra == "dev"
Requires-Dist: coverage; extra == "dev"
Requires-Dist: inflection; extra == "dev"
Requires-Dist: jupyter; extra == "dev"
Requires-Dist: mypy; extra == "dev"
Requires-Dist: nbconvert; extra == "dev"
Requires-Dist: nbsphinx; extra == "dev"
Requires-Dist: progressbar2; extra == "dev"
Requires-Dist: pytest>=4.2.0; extra == "dev"
Requires-Dist: pytest-cov; extra == "dev"
Requires-Dist: pytz; extra == "dev"
Requires-Dist: recommonmark; extra == "dev"
Requires-Dist: requests_mock; extra == "dev"
Requires-Dist: responses; extra == "dev"
Requires-Dist: sphinx>=1.8.0; extra == "dev"
Requires-Dist: sphinx-notfound-page; extra == "dev"
Requires-Dist: sphinx_rtd_theme; extra == "dev"
Requires-Dist: types-decorator; extra == "dev"
Requires-Dist: types-python-dateutil; extra == "dev"
Requires-Dist: types-pytz; extra == "dev"
Requires-Dist: types-PyYAML; extra == "dev"
Requires-Dist: types-requests; extra == "dev"
Requires-Dist: types-setuptools; extra == "dev"
Requires-Dist: types-simplejson; extra == "dev"
Requires-Dist: capirca; extra == "dev"
Requires-Dist: absl-py>=0.8.0; extra == "dev"
Dynamic: license-file
